{"metadata": {"dbt_schema_version": "https://schemas.getdbt.com/dbt/run-results/v6.json", "dbt_version": "1.11.12", "generated_at": "2026-07-04T17:54:08.116464Z", "invocation_id": "a0442ad9-6913-4212-a4ea-f877bd84b087", "invocation_started_at": "2026-07-04T17:54:06.888649Z", "env": {}}, "results": [{"status": "success", "timing": [{"name": "compile", "started_at": "2026-07-04T17:54:07.966129Z", "completed_at": "2026-07-04T17:54:07.987872Z"}, {"name": "execute", "started_at": "2026-07-04T17:54:07.989876Z", "completed_at": "2026-07-04T17:54:07.989894Z"}], "thread_id": "Thread-1 (worker)", "execution_time": 0.02825140953063965, "adapter_response": {}, "message": null, "failures": null, "unique_id": "model.fresh_segments.stg_fresh_segments__interest_map", "compiled": true, "compiled_code": "with source as (\n    select *\n    from \"fresh_segments\".\"fresh_segments\".\"interest_map\"\n),\n\nrenamed as (\n    select\n        id::integer as interest_id,\n        trim(interest_name) as interest_name,\n        nullif(trim(interest_summary), '') as interest_summary,\n        created_at::timestamp as created_at,\n        last_modified::timestamp as last_modified\n    from source\n)\n\nselect *\nfrom renamed", "relation_name": "\"fresh_segments\".\"analytics_analytics_staging\".\"stg_fresh_segments__interest_map\"", "batch_results": null}, {"status": "success", "timing": [{"name": "compile", "started_at": "2026-07-04T17:54:07.976175Z", "completed_at": "2026-07-04T17:54:07.989083Z"}, {"name": "execute", "started_at": "2026-07-04T17:54:07.991746Z", "completed_at": "2026-07-04T17:54:07.991761Z"}], "thread_id": "Thread-3 (worker)", "execution_time": 0.027425527572631836, "adapter_response": {}, "message": null, "failures": null, "unique_id": "test.fresh_segments.source_not_null_fresh_segments_interest_map_id.1b76d3d7c7", "compiled": true, "compiled_code": "\n    \n    \n\n\n\nselect id\nfrom \"fresh_segments\".\"fresh_segments\".\"interest_map\"\nwhere id is null\n\n\n", "relation_name": null, "batch_results": null}, {"status": "success", "timing": [{"name": "compile", "started_at": "2026-07-04T17:54:07.973421Z", "completed_at": "2026-07-04T17:54:07.990782Z"}, {"name": "execute", "started_at": "2026-07-04T17:54:07.993344Z", "completed_at": "2026-07-04T17:54:07.993362Z"}], "thread_id": "Thread-2 (worker)", "execution_time": 0.03016519546508789, "adapter_response": {}, "message": null, "failures": null, "unique_id": "model.fresh_segments.stg_fresh_segments__interest_metrics", "compiled": true, "compiled_code": "with source as (\n    select *\n    from \"fresh_segments\".\"fresh_segments\".\"interest_metrics\"\n),\n\ncleaned as (\n    select\n        nullif(_month, 'NULL')::integer as month_number,\n        nullif(_year, 'NULL')::integer as year_number,\n\tmonth_year as month_start_date,\n\tnullif(interest_id, 'NULL')::integer as interest_id,\n        composition::numeric(10, 4) as composition,\n        index_value::numeric(10, 4) as index_value,\n        ranking::integer as ranking,\n        percentile_ranking::numeric(10, 4) as percentile_ranking\n    from source\n    where month_year is not null\n)\n\nselect *\nfrom cleaned\nwhere interest_id is not null", "relation_name": "\"fresh_segments\".\"analytics_analytics_staging\".\"stg_fresh_segments__interest_metrics\"", "batch_results": null}, {"status": "success", "timing": [{"name": "compile", "started_at": "2026-07-04T17:54:07.984292Z", "completed_at": "2026-07-04T17:54:07.995998Z"}, {"name": "execute", "started_at": "2026-07-04T17:54:07.999253Z", "completed_at": "2026-07-04T17:54:07.999267Z"}], "thread_id": "Thread-4 (worker)", "execution_time": 0.03434324264526367, "adapter_response": {}, "message": null, "failures": null, "unique_id": "test.fresh_segments.source_not_null_fresh_segments_interest_map_interest_name.d9bc4aed7b", "compiled": true, "compiled_code": "\n    \n    \n\n\n\nselect interest_name\nfrom \"fresh_segments\".\"fresh_segments\".\"interest_map\"\nwhere interest_name is null\n\n\n", "relation_name": null, "batch_results": null}, {"status": "success", "timing": [{"name": "compile", "started_at": "2026-07-04T17:54:08.003451Z", "completed_at": "2026-07-04T17:54:08.016130Z"}, {"name": "execute", "started_at": "2026-07-04T17:54:08.018484Z", "completed_at": "2026-07-04T17:54:08.018495Z"}], "thread_id": "Thread-1 (worker)", "execution_time": 0.021927833557128906, "adapter_response": {}, "message": null, "failures": null, "unique_id": "test.fresh_segments.source_unique_fresh_segments_interest_map_id.b172de1766", "compiled": true, "compiled_code": "\n    \n    \n\nselect\n    id as unique_field,\n    count(*) as n_records\n\nfrom \"fresh_segments\".\"fresh_segments\".\"interest_map\"\nwhere id is not null\ngroup by id\nhaving count(*) > 1\n\n\n", "relation_name": null, "batch_results": null}, {"status": "success", "timing": [{"name": "compile", "started_at": "2026-07-04T17:54:08.010145Z", "completed_at": "2026-07-04T17:54:08.016745Z"}, {"name": "execute", "started_at": "2026-07-04T17:54:08.019295Z", "completed_at": "2026-07-04T17:54:08.019304Z"}], "thread_id": "Thread-3 (worker)", "execution_time": 0.020914077758789062, "adapter_response": {}, "message": null, "failures": null, "unique_id": "model.fresh_segments.dim_interest", "compiled": true, "compiled_code": "select\n    interest_id,\n    interest_name,\n    interest_summary,\n    created_at,\n    last_modified\nfrom \"fresh_segments\".\"analytics_analytics_staging\".\"stg_fresh_segments__interest_map\"", "relation_name": "\"fresh_segments\".\"analytics_analytics\".\"dim_interest\"", "batch_results": null}, {"status": "success", "timing": [{"name": "compile", "started_at": "2026-07-04T17:54:08.012242Z", "completed_at": "2026-07-04T17:54:08.017923Z"}, {"name": "execute", "started_at": "2026-07-04T17:54:08.023624Z", "completed_at": "2026-07-04T17:54:08.023633Z"}], "thread_id": "Thread-2 (worker)", "execution_time": 0.022820472717285156, "adapter_response": {}, "message": null, "failures": null, "unique_id": "test.fresh_segments.not_null_stg_fresh_segments__interest_map_interest_id.cb2203fd48", "compiled": true, "compiled_code": "\n    \n    \n\n\n\nselect interest_id\nfrom \"fresh_segments\".\"analytics_analytics_staging\".\"stg_fresh_segments__interest_map\"\nwhere interest_id is null\n\n\n", "relation_name": null, "batch_results": null}, {"status": "success", "timing": [{"name": "compile", "started_at": "2026-07-04T17:54:08.020081Z", "completed_at": "2026-07-04T17:54:08.025816Z"}, {"name": "execute", "started_at": "2026-07-04T17:54:08.027780Z", "completed_at": "2026-07-04T17:54:08.027788Z"}], "thread_id": "Thread-4 (worker)", "execution_time": 0.016061782836914062, "adapter_response": {}, "message": null, "failures": null, "unique_id": "test.fresh_segments.not_null_stg_fresh_segments__interest_map_interest_name.0ae9f29b9f", "compiled": true, "compiled_code": "\n    \n    \n\n\n\nselect interest_name\nfrom \"fresh_segments\".\"analytics_analytics_staging\".\"stg_fresh_segments__interest_map\"\nwhere interest_name is null\n\n\n", "relation_name": null, "batch_results": null}, {"status": "success", "timing": [{"name": "compile", "started_at": "2026-07-04T17:54:08.030307Z", "completed_at": "2026-07-04T17:54:08.043396Z"}, {"name": "execute", "started_at": "2026-07-04T17:54:08.045229Z", "completed_at": "2026-07-04T17:54:08.045238Z"}], "thread_id": "Thread-1 (worker)", "execution_time": 0.019081830978393555, "adapter_response": {}, "message": null, "failures": null, "unique_id": "test.fresh_segments.unique_stg_fresh_segments__interest_map_interest_id.9b83476024", "compiled": true, "compiled_code": "\n    \n    \n\nselect\n    interest_id as unique_field,\n    count(*) as n_records\n\nfrom \"fresh_segments\".\"analytics_analytics_staging\".\"stg_fresh_segments__interest_map\"\nwhere interest_id is not null\ngroup by interest_id\nhaving count(*) > 1\n\n\n", "relation_name": null, "batch_results": null}, {"status": "success", "timing": [{"name": "compile", "started_at": "2026-07-04T17:54:08.033455Z", "completed_at": "2026-07-04T17:54:08.043902Z"}, {"name": "execute", "started_at": "2026-07-04T17:54:08.045818Z", "completed_at": "2026-07-04T17:54:08.045826Z"}], "thread_id": "Thread-3 (worker)", "execution_time": 0.019230127334594727, "adapter_response": {}, "message": null, "failures": null, "unique_id": "test.fresh_segments.not_null_stg_fresh_segments__interest_metrics_interest_id.960d25dbf1", "compiled": true, "compiled_code": "\n    \n    \n\n\n\nselect interest_id\nfrom \"fresh_segments\".\"analytics_analytics_staging\".\"stg_fresh_segments__interest_metrics\"\nwhere interest_id is null\n\n\n", "relation_name": null, "batch_results": null}, {"status": "success", "timing": [{"name": "compile", "started_at": "2026-07-04T17:54:08.037729Z", "completed_at": "2026-07-04T17:54:08.044310Z"}, {"name": "execute", "started_at": "2026-07-04T17:54:08.046713Z", "completed_at": "2026-07-04T17:54:08.046722Z"}], "thread_id": "Thread-2 (worker)", "execution_time": 0.019490718841552734, "adapter_response": {}, "message": null, "failures": null, "unique_id": "test.fresh_segments.not_null_stg_fresh_segments__interest_metrics_month_start_date.e246812525", "compiled": true, "compiled_code": "\n    \n    \n\n\n\nselect month_start_date\nfrom \"fresh_segments\".\"analytics_analytics_staging\".\"stg_fresh_segments__interest_metrics\"\nwhere month_start_date is null\n\n\n", "relation_name": null, "batch_results": null}, {"status": "success", "timing": [{"name": "compile", "started_at": "2026-07-04T17:54:08.047450Z", "completed_at": "2026-07-04T17:54:08.053664Z"}, {"name": "execute", "started_at": "2026-07-04T17:54:08.056299Z", "completed_at": "2026-07-04T17:54:08.056316Z"}], "thread_id": "Thread-4 (worker)", "execution_time": 0.013832807540893555, "adapter_response": {}, "message": null, "failures": null, "unique_id": "test.fresh_segments.not_null_stg_fresh_segments__interest_metrics_ranking.d93144cef1", "compiled": true, "compiled_code": "\n    \n    \n\n\n\nselect ranking\nfrom \"fresh_segments\".\"analytics_analytics_staging\".\"stg_fresh_segments__interest_metrics\"\nwhere ranking is null\n\n\n", "relation_name": null, "batch_results": null}, {"status": "success", "timing": [{"name": "compile", "started_at": "2026-07-04T17:54:08.059227Z", "completed_at": "2026-07-04T17:54:08.072364Z"}, {"name": "execute", "started_at": "2026-07-04T17:54:08.075036Z", "completed_at": "2026-07-04T17:54:08.075046Z"}], "thread_id": "Thread-1 (worker)", "execution_time": 0.02211618423461914, "adapter_response": {}, "message": null, "failures": null, "unique_id": "model.fresh_segments.fct_interest_monthly_performance", "compiled": true, "compiled_code": "with metrics as ( -- take the interest metrics from the staging table \n    select *\n    from \"fresh_segments\".\"analytics_analytics_staging\".\"stg_fresh_segments__interest_metrics\"\n),\n\ninterest as ( -- take the interest details from the dimension table  \n    select *\n    from \"fresh_segments\".\"analytics_analytics\".\"dim_interest\"\n)\n\nselect\n    m.month_start_date,\n    m.year_number,\n    m.month_number,\n    m.interest_id,\n    i.interest_name,\n    i.interest_summary,\n    m.composition,\n    m.index_value,\n    m.ranking,\n    m.percentile_ranking,\n    case\n        when m.ranking <= 10 then 'top_10'\n        when m.ranking <= 100 then 'top_100'\n        else 'long_tail'\n    end as ranking_bucket\nfrom metrics as m\nleft join interest as i\n    on m.interest_id = i.interest_id", "relation_name": "\"fresh_segments\".\"analytics_analytics\".\"fct_interest_monthly_performance\"", "batch_results": null}, {"status": "success", "timing": [{"name": "compile", "started_at": "2026-07-04T17:54:08.067935Z", "completed_at": "2026-07-04T17:54:08.073121Z"}, {"name": "execute", "started_at": "2026-07-04T17:54:08.075803Z", "completed_at": "2026-07-04T17:54:08.075812Z"}], "thread_id": "Thread-2 (worker)", "execution_time": 0.020923376083374023, "adapter_response": {}, "message": null, "failures": null, "unique_id": "test.fresh_segments.not_null_dim_interest_interest_name.984fd8035c", "compiled": true, "compiled_code": "\n    \n    \n\n\n\nselect interest_name\nfrom \"fresh_segments\".\"analytics_analytics\".\"dim_interest\"\nwhere interest_name is null\n\n\n", "relation_name": null, "batch_results": null}, {"status": "success", "timing": [{"name": "compile", "started_at": "2026-07-04T17:54:08.063300Z", "completed_at": "2026-07-04T17:54:08.074246Z"}, {"name": "execute", "started_at": "2026-07-04T17:54:08.080104Z", "completed_at": "2026-07-04T17:54:08.080132Z"}], "thread_id": "Thread-3 (worker)", "execution_time": 0.02608513832092285, "adapter_response": {}, "message": null, "failures": null, "unique_id": "test.fresh_segments.not_null_dim_interest_interest_id.4c03e9a469", "compiled": true, "compiled_code": "\n    \n    \n\n\n\nselect interest_id\nfrom \"fresh_segments\".\"analytics_analytics\".\"dim_interest\"\nwhere interest_id is null\n\n\n", "relation_name": null, "batch_results": null}, {"status": "success", "timing": [{"name": "compile", "started_at": "2026-07-04T17:54:08.076571Z", "completed_at": "2026-07-04T17:54:08.082394Z"}, {"name": "execute", "started_at": "2026-07-04T17:54:08.082982Z", "completed_at": "2026-07-04T17:54:08.082990Z"}], "thread_id": "Thread-4 (worker)", "execution_time": 0.011367082595825195, "adapter_response": {}, "message": null, "failures": null, "unique_id": "test.fresh_segments.unique_dim_interest_interest_id.0fcb831c97", "compiled": true, "compiled_code": "\n    \n    \n\nselect\n    interest_id as unique_field,\n    count(*) as n_records\n\nfrom \"fresh_segments\".\"analytics_analytics\".\"dim_interest\"\nwhere interest_id is not null\ngroup by interest_id\nhaving count(*) > 1\n\n\n", "relation_name": null, "batch_results": null}, {"status": "success", "timing": [{"name": "compile", "started_at": "2026-07-04T17:54:08.090391Z", "completed_at": "2026-07-04T17:54:08.101307Z"}, {"name": "execute", "started_at": "2026-07-04T17:54:08.109287Z", "completed_at": "2026-07-04T17:54:08.109298Z"}], "thread_id": "Thread-4 (worker)", "execution_time": 0.024649620056152344, "adapter_response": {}, "message": null, "failures": null, "unique_id": "test.fresh_segments.accepted_values_fct_interest_monthly_performance_ranking_bucket__top_10__top_100__long_tail.c02772ca5e", "compiled": true, "compiled_code": "\n    \n    \n\nwith all_values as (\n\n    select\n        ranking_bucket as value_field,\n        count(*) as n_records\n\n    from \"fresh_segments\".\"analytics_analytics\".\"fct_interest_monthly_performance\"\n    group by ranking_bucket\n\n)\n\nselect *\nfrom all_values\nwhere value_field not in (\n    'top_10','top_100','long_tail'\n)\n\n\n", "relation_name": null, "batch_results": null}, {"status": "success", "timing": [{"name": "compile", "started_at": "2026-07-04T17:54:08.094512Z", "completed_at": "2026-07-04T17:54:08.107365Z"}, {"name": "execute", "started_at": "2026-07-04T17:54:08.110122Z", "completed_at": "2026-07-04T17:54:08.110132Z"}], "thread_id": "Thread-1 (worker)", "execution_time": 0.02408766746520996, "adapter_response": {}, "message": null, "failures": null, "unique_id": "test.fresh_segments.not_null_fct_interest_monthly_performance_interest_id.f6c50be413", "compiled": true, "compiled_code": "\n    \n    \n\n\n\nselect interest_id\nfrom \"fresh_segments\".\"analytics_analytics\".\"fct_interest_monthly_performance\"\nwhere interest_id is null\n\n\n", "relation_name": null, "batch_results": null}, {"status": "success", "timing": [{"name": "compile", "started_at": "2026-07-04T17:54:08.098158Z", "completed_at": "2026-07-04T17:54:08.108760Z"}, {"name": "execute", "started_at": "2026-07-04T17:54:08.110992Z", "completed_at": "2026-07-04T17:54:08.110997Z"}], "thread_id": "Thread-2 (worker)", "execution_time": 0.022928714752197266, "adapter_response": {}, "message": null, "failures": null, "unique_id": "test.fresh_segments.not_null_fct_interest_monthly_performance_month_start_date.d3288e54b4", "compiled": true, "compiled_code": "\n    \n    \n\n\n\nselect month_start_date\nfrom \"fresh_segments\".\"analytics_analytics\".\"fct_interest_monthly_performance\"\nwhere month_start_date is null\n\n\n", "relation_name": null, "batch_results": null}, {"status": "success", "timing": [{"name": "compile", "started_at": "2026-07-04T17:54:08.101792Z", "completed_at": "2026-07-04T17:54:08.111768Z"}, {"name": "execute", "started_at": "2026-07-04T17:54:08.112608Z", "completed_at": "2026-07-04T17:54:08.112617Z"}], "thread_id": "Thread-3 (worker)", "execution_time": 0.02331399917602539, "adapter_response": {}, "message": null, "failures": null, "unique_id": "test.fresh_segments.relationships_fct_interest_monthly_performance_interest_id__interest_id__ref_dim_interest_.a8d887cd7e", "compiled": true, "compiled_code": "\n    \n    \n\nwith child as (\n    select interest_id as from_field\n    from \"fresh_segments\".\"analytics_analytics\".\"fct_interest_monthly_performance\"\n    where interest_id is not null\n),\n\nparent as (\n    select interest_id as to_field\n    from \"fresh_segments\".\"analytics_analytics\".\"dim_interest\"\n)\n\nselect\n    from_field\n\nfrom child\nleft join parent\n    on child.from_field = parent.to_field\n\nwhere parent.to_field is null\n\n\n", "relation_name": null, "batch_results": null}], "elapsed_time": 0.20963215827941895, "args": {"introspect": true, "require_yaml_configuration_for_mf_time_spines": false, "populate_cache": true, "upload_to_artifacts_ingest_api": false, "invocation_command": "dbt compile --target-path sanity_sql/target --no-partial-parse", "version_check": true, "warn_error_options": {"error": [], "warn": [], "silence": []}, "log_path": "/home/sang/Desktop/current_repos/diesel_dbm/dbt_fresh_segments/logs", "log_file_max_bytes": 10485760, "inject_ephemeral_ctes": true, "macro_debugging": false, "favor_state": false, "log_level_file": "debug", "log_level": "info", "require_explicit_package_overrides_for_builtin_materializations": true, "require_nested_cumulative_type_params": false, "send_anonymous_usage_stats": true, "log_format_file": "debug", "state_modified_compare_more_unrendered_values": false, "target_path": "sanity_sql/target", "use_colors_file": true, "validate_macro_args": false, "quiet": false, "skip_nodes_if_on_run_start_fails": false, "which": "compile", "require_unique_project_resource_names": false, "select": [], "show_all_deprecations": false, "source_freshness_run_project_hooks": true, "show_resource_report": false, "printer_width": 80, "output": "text", "static_parser": true, "sqlparse": {"MAX_GROUPING_DEPTH": null, "MAX_GROUPING_TOKENS": null}, "require_resource_names_without_spaces": true, "exclude": [], "use_colors": true, "partial_parse_file_diff": true, "partial_parse": false, "defer": false, "require_all_warnings_handled_by_warn_error": false, "print": true, "strict_mode": false, "use_fast_test_edges": false, "cache_selected_only": false, "write_json": true, "require_generic_test_arguments_property": true, "profiles_dir": "/home/sang/.dbt", "indirect_selection": "eager", "vars": {}, "project_dir": "/home/sang/Desktop/current_repos/diesel_dbm/dbt_fresh_segments", "require_batched_execution_for_custom_microbatch_strategy": false, "require_ref_searches_node_package_before_root": false, "log_format": "default", "empty": false, "state_modified_compare_vars": false}}